{
  "lexicon": 1,
  "id": "xyz.atboards.reply",
  "defs": {
    "main": {
      "type": "record",
      "key": "tid",
      "record": {
        "type": "object",
        "required": [
          "subject",
          "body",
          "createdAt"
        ],
        "properties": {
          "subject": {
            "type": "string",
            "format": "at-uri"
          },
          "body": {
            "type": "string",
            "maxLength": 10000
          },
          "quote": {
            "type": "string",
            "format": "at-uri"
          },
          "createdAt": {
            "type": "string",
            "format": "datetime"
          },
          "attachments": {
            "type": "array",
            "maxLength": 10,
            "items": {
              "type": "ref",
              "ref": "#attachment"
            }
          },
          "updatedAt": {
            "type": "string",
            "format": "datetime"
          }
        }
      }
    },
    "attachment": {
      "type": "object",
      "required": ["file", "name"],
      "properties": {
        "file": {
          "type": "blob",
          "accept": ["*/*"],
          "maxSize": 1000000
        },
        "name": {
          "type": "string",
          "maxLength": 256
        }
      }
    }
  }
}
